usps_client/__init__.py
usps_client/base_model.py
usps_client/client.py
usps_client/models.py
usps_client/shims.py
usps_client/version.py
usps_client-0.2.data/data/requirements/requirements.txt
usps_client-0.2.dist-info/LICENSE.md
usps_client-0.2.dist-info/METADATA
usps_client-0.2.dist-info/WHEEL
usps_client-0.2.dist-info/top_level.txt
usps_client-0.2.dist-info/RECORD
