Metadata-Version: 2.1
Name: usps-client
Version: 0.2
Summary: An unofficial client for the USPS Web Tools APIs
Home-page: https://github.com/macro1/usps-client
Author: Micah Denbraver
Author-email: macromicah@gmail.com
License: UNKNOWN
Platform: UNKNOWN
Classifier: Development Status :: 3 - Alpha
Classifier: License :: OSI Approved :: ISC License (ISCL)
Classifier: Programming Language :: Python
Classifier: Programming Language :: Python :: 2
Classifier: Programming Language :: Python :: 2.7
Classifier: Programming Language :: Python :: 3
Classifier: Operating System :: OS Independent
Requires-Dist: attrs (>=17)
Requires-Dist: inflection
Requires-Dist: urllib3[secure] (<2,>=1.9)
